dextro/__init__.py
dextro/console/entrypoint.py
dextro/console/index_dataset.py
dextro/enrichers.py
dextro/indexing.py
dextro/loaders.py
dextro/torch.py
dextro/types.py
dextro-0.1.2.dist-info/LICENSE
dextro-0.1.2.dist-info/METADATA
dextro-0.1.2.dist-info/WHEEL
dextro-0.1.2.dist-info/entry_points.txt
dextro-0.1.2.dist-info/RECORD
