Metadata-Version: 2.1
Name: dextro
Version: 0.1.2
Summary: 
Author: Kristian Klemon
Author-email: kristian.klemon@gmail.com
Requires-Python: >=3.10,<4.0
Classifier: Programming Language :: Python :: 3
Classifier: Programming Language :: Python :: 3.10
Classifier: Programming Language :: Python :: 3.11
Classifier: Programming Language :: Python :: 3.12
Provides-Extra: all
Provides-Extra: language-detection
Provides-Extra: torch
Requires-Dist: lingua-language-detector (>=2.0.2,<3.0.0) ; extra == "language-detection" or extra == "all"
Requires-Dist: polars (>=1.13.1,<2.0.0)
Requires-Dist: pyarrow (>=18.0.0,<19.0.0)
Requires-Dist: torch (>=2.2.0,<3.0.0) ; extra == "torch" or extra == "all"
Requires-Dist: tqdm (>=4.67.0,<5.0.0)
